lfo/lfo_dump.py
lfo/__init__.pyi
lfo/__init__.py
lfo/py.typed
lfo/_lfo.cpython-314-darwin.so
lfo-0.0.6.dist-info/RECORD
lfo-0.0.6.dist-info/WHEEL
lfo-0.0.6.dist-info/entry_points.txt
lfo-0.0.6.dist-info/top_level.txt
lfo-0.0.6.dist-info/METADATA
lfo-0.0.6.dist-info/licenses/LICENSE
