Metadata-Version: 2.4
Name: lfo
Version: 0.0.6
Summary: A Low Frequency Oscillator
Author-email: Michael Lamertz <michael.lamertz@gmail.com>
License-Expression: MIT
Project-URL: homepage, https://github.com/dickerdackel/lfo
Project-URL: bugtracker, https://github.com/DickerDackel/lfo/issues
Classifier: Development Status :: 3 - Alpha
Classifier: Intended Audience :: Developers
Classifier: Topic :: Games/Entertainment
Classifier: Topic :: Software Development :: Libraries :: pygame
License-File: LICENSE
Dynamic: license-file
